{
  "project_info": {
    "project_number": "277764955988",
    "project_id": "heartcare-6dc4b",
    "storage_bucket": "heartcare-6dc4b.appspot.com"
  },
  "client": [
    {
      "client_info": {
        "mobilesdk_app_id": "1:277764955988:android:5c5fb4727064ffa8b6b2c1",
        "android_client_info": {
          "package_name": "com.blez.heart_care"
        }
      },
      "oauth_client": [
        {
          "client_id": "277764955988-put1mpjvf8utpg6t9rfm52k97r3rb485.apps.googleusercontent.com",
          "client_type": 1,
          "android_info": {
            "package_name": "com.blez.heart_care",
            "certificate_hash": "6f560f2141fc6f9dc94d480e77d6ed6571c89054"
          }
        },
        {
          "client_id": "277764955988-s3nnsfpf9rf3racmv6qd6hh5gh40qf5m.apps.googleusercontent.com",
          "client_type": 3
        }
      ],
      "api_key": [
        {
          "current_key": "AIzaSyD0DZMRRFxob8MXXj1nf9h4WjmUHc5qAWo"
        }
      ],
      "services": {
        "appinvite_service": {
          "other_platform_oauth_client": [
            {
              "client_id": "277764955988-s3nnsfpf9rf3racmv6qd6hh5gh40qf5m.apps.googleusercontent.com",
              "client_type": 3
            }
          ]
        }
      }
    }
  ],
  "configuration_version": "1"
}